odoo/addons/test_ssi_state_change_constrain_mixin/README.rst
odoo/addons/test_ssi_state_change_constrain_mixin/__init__.py
odoo/addons/test_ssi_state_change_constrain_mixin/__manifest__.py
odoo/addons/test_ssi_state_change_constrain_mixin/models/__init__.py
odoo/addons/test_ssi_state_change_constrain_mixin/models/test_state_change_constrain.py
odoo/addons/test_ssi_state_change_constrain_mixin/security/ir.model.access.csv
odoo/addons/test_ssi_state_change_constrain_mixin/static/description/icon.png
odoo/addons/test_ssi_state_change_constrain_mixin/views/test_state_change_constrain_view.xml
odoo14_addon_test_ssi_state_change_constrain_mixin-14.0.1.3.0.dist-info/METADATA
odoo14_addon_test_ssi_state_change_constrain_mixin-14.0.1.3.0.dist-info/WHEEL
odoo14_addon_test_ssi_state_change_constrain_mixin-14.0.1.3.0.dist-info/top_level.txt
odoo14_addon_test_ssi_state_change_constrain_mixin-14.0.1.3.0.dist-info/RECORD
